sxolar/__init__.py
sxolar/_version.py
sxolar/config.py
sxolar/summary.py
sxolar/api/__init__.py
sxolar/api/arxiv.py
sxolar/api/search.py
sxolar/bin/__init__.py
sxolar/bin/sxolar.py
sxolar/util/__init__.py
sxolar/util/gmail.py
sxolar-0.2.3.dist-info/LICENSE
sxolar-0.2.3.dist-info/METADATA
sxolar-0.2.3.dist-info/WHEEL
sxolar-0.2.3.dist-info/entry_points.txt
sxolar-0.2.3.dist-info/top_level.txt
sxolar-0.2.3.dist-info/RECORD
