Metadata-Version: 2.1
Name: sxolar
Version: 0.2.3
Summary: Scholar's tools for working with Arxiv
Author-email: James Kennington <jameswkennington@gmail.com>
License: MPL-2.0
Project-URL: Homepage, https://github.com/JWKennington/sxolar
Project-URL: Documentation, https://www.sxolar.org
Project-URL: Issues, https://github.com/JWKennington/sxolar/issues
Classifier: Programming Language :: Python :: 3
Classifier: License :: OSI Approved :: Mozilla Public License 2.0 (MPL 2.0)
Classifier: Operating System :: OS Independent
Requires-Python: >=3.9
License-File: LICENSE
Requires-Dist: requests
Requires-Dist: defusedxml
Requires-Dist: requests_ratelimiter
Requires-Dist: ruamel.yaml
Provides-Extra: docs
Requires-Dist: mkdocs; extra == "docs"
Requires-Dist: mkdocstrings; extra == "docs"
Requires-Dist: mkdocstrings-python; extra == "docs"
Requires-Dist: mkdocs-material; extra == "docs"
Requires-Dist: pymdown-extensions; extra == "docs"
Provides-Extra: lint
Requires-Dist: black; extra == "lint"
Requires-Dist: flake8; extra == "lint"
Requires-Dist: flake8-bandit; extra == "lint"
Requires-Dist: flake8-black; extra == "lint"
Requires-Dist: flake8-bugbear; extra == "lint"
Requires-Dist: flake8-future-annotations; extra == "lint"
Requires-Dist: flake8-isort; extra == "lint"
Requires-Dist: flake8-logging-format; extra == "lint"
Requires-Dist: flake8-pyproject; extra == "lint"
Requires-Dist: isort; extra == "lint"
Requires-Dist: mypy; extra == "lint"
Requires-Dist: mypy-extensions; extra == "lint"
Provides-Extra: test
Requires-Dist: pytest; extra == "test"
Requires-Dist: pytest-cov; extra == "test"
Requires-Dist: pytest-markdown-docs; extra == "test"
Provides-Extra: dev
Requires-Dist: sxolar[docs]; extra == "dev"
Requires-Dist: sxolar[test]; extra == "dev"
